odoo/addons/account_reporting_volume/README.rst
odoo/addons/account_reporting_volume/__init__.py
odoo/addons/account_reporting_volume/__manifest__.py
odoo/addons/account_reporting_volume/i18n/account_reporting_volume.pot
odoo/addons/account_reporting_volume/i18n/es.po
odoo/addons/account_reporting_volume/models/__init__.py
odoo/addons/account_reporting_volume/models/account_invoice_report.py
odoo/addons/account_reporting_volume/readme/CONTRIBUTORS.rst
odoo/addons/account_reporting_volume/readme/DESCRIPTION.rst
odoo/addons/account_reporting_volume/readme/USAGE.rst
odoo/addons/account_reporting_volume/static/description/icon.png
odoo/addons/account_reporting_volume/static/description/index.html
odoo13_addon_account_reporting_volume-13.0.1.0.1.dev5.dist-info/METADATA
odoo13_addon_account_reporting_volume-13.0.1.0.1.dev5.dist-info/WHEEL
odoo13_addon_account_reporting_volume-13.0.1.0.1.dev5.dist-info/top_level.txt
odoo13_addon_account_reporting_volume-13.0.1.0.1.dev5.dist-info/RECORD
